layerlens/__init__.py
layerlens/__pycache__/__init__.cpython-313.pyc
layerlens/core/__init__.py
layerlens/core/fidelity_metrics.py
layerlens/core/layer_extractor.py
layerlens/core/model_hooks.py
layerlens/core/stitching_engine.py
layerlens/core/surrogate_builder.py
layerlens/core/__pycache__/__init__.cpython-313.pyc
layerlens/core/__pycache__/fidelity_metrics.cpython-313.pyc
layerlens/core/__pycache__/layer_extractor.cpython-313.pyc
layerlens/core/__pycache__/model_hooks.cpython-313.pyc
layerlens/core/__pycache__/stitching_engine.cpython-313.pyc
layerlens/core/__pycache__/surrogate_builder.cpython-313.pyc
layerlens/monitoring/__init__.py
layerlens/monitoring/alert_system.py
layerlens/monitoring/drift_detector.py
layerlens/monitoring/failure_localizer.py
layerlens/monitoring/logging_tools.py
layerlens/monitoring/__pycache__/__init__.cpython-313.pyc
layerlens/monitoring/__pycache__/alert_system.cpython-313.pyc
layerlens/monitoring/__pycache__/drift_detector.cpython-313.pyc
layerlens/monitoring/__pycache__/failure_localizer.cpython-313.pyc
layerlens/monitoring/__pycache__/logging_tools.cpython-313.pyc
layerlens/utils/__init__.py
layerlens/utils/config.py
layerlens/utils/data_utils.py
layerlens/utils/model_utils.py
layerlens/utils/plot_utils.py
layerlens/utils/__pycache__/__init__.cpython-313.pyc
layerlens/utils/__pycache__/config.cpython-313.pyc
layerlens/utils/__pycache__/data_utils.cpython-313.pyc
layerlens/utils/__pycache__/model_utils.cpython-313.pyc
layerlens/utils/__pycache__/plot_utils.cpython-313.pyc
layerlens/visualization/__init__.py
layerlens/visualization/dashboard.py
layerlens/visualization/feature_flow.py
layerlens/visualization/heatmap_generator.py
layerlens/visualization/layer_graph.py
layerlens/visualization/__pycache__/__init__.cpython-313.pyc
layerlens/visualization/__pycache__/dashboard.cpython-313.pyc
layerlens/visualization/__pycache__/feature_flow.cpython-313.pyc
layerlens/visualization/__pycache__/heatmap_generator.cpython-313.pyc
layerlens-0.1.1.dist-info/licenses/LICENSE
layerlens-0.1.1.dist-info/METADATA
layerlens-0.1.1.dist-info/WHEEL
layerlens-0.1.1.dist-info/top_level.txt
layerlens-0.1.1.dist-info/RECORD
